tiledb/plot/widget/__init__.py
tiledb/plot/widget/_frontend.py
tiledb/plot/widget/_version.py
tiledb/plot/widget/visualize.py
tiledb/plot/widget/labextension/package.json
tiledb/plot/widget/labextension/static/269.95526110903a310aa035.js
tiledb/plot/widget/labextension/static/568.c4a74cc6f2b28e70fb40.js
tiledb/plot/widget/labextension/static/747.c6c02d7ea625bc1a4bb7.js
tiledb/plot/widget/labextension/static/remoteEntry.916456d108fa7106aabd.js
tiledb/plot/widget/labextension/static/style.js
tiledb/plot/widget/labextension/static/third-party-licenses.json
tiledb_plot_widget-1.1.0.data/data/share/jupyter/labextensions/@tiledb-inc/tiledb-plot-widget/install.json
tiledb_plot_widget-1.1.0.data/data/share/jupyter/labextensions/@tiledb-inc/tiledb-plot-widget/package.json
tiledb_plot_widget-1.1.0.data/data/share/jupyter/labextensions/@tiledb-inc/tiledb-plot-widget/static/269.95526110903a310aa035.js
tiledb_plot_widget-1.1.0.data/data/share/jupyter/labextensions/@tiledb-inc/tiledb-plot-widget/static/568.c4a74cc6f2b28e70fb40.js
tiledb_plot_widget-1.1.0.data/data/share/jupyter/labextensions/@tiledb-inc/tiledb-plot-widget/static/747.c6c02d7ea625bc1a4bb7.js
tiledb_plot_widget-1.1.0.data/data/share/jupyter/labextensions/@tiledb-inc/tiledb-plot-widget/static/remoteEntry.916456d108fa7106aabd.js
tiledb_plot_widget-1.1.0.data/data/share/jupyter/labextensions/@tiledb-inc/tiledb-plot-widget/static/style.js
tiledb_plot_widget-1.1.0.data/data/share/jupyter/labextensions/@tiledb-inc/tiledb-plot-widget/static/third-party-licenses.json
tiledb_plot_widget-1.1.0.dist-info/LICENSE
tiledb_plot_widget-1.1.0.dist-info/METADATA
tiledb_plot_widget-1.1.0.dist-info/WHEEL
tiledb_plot_widget-1.1.0.dist-info/top_level.txt
tiledb_plot_widget-1.1.0.dist-info/RECORD
